bigbang/__init__.py
bigbang/import_nodes.py
bigbang/import_relationships.py
bigbang/load_dot_env.py
bigbang/entities/__init__.py
bigbang/entities/neo4j_instance.py
bigbang/entities/neo4j_properties.py
bigbang/entities/neo4j_property.py
bigbang/entities/neo4j_property_bool.py
bigbang/entities/neo4j_property_date.py
bigbang/entities/neo4j_property_datetime.py
bigbang/entities/neo4j_property_float.py
bigbang/entities/neo4j_property_int.py
bigbang/entities/neo4j_property_null.py
bigbang/entities/neo4j_property_str.py
bigbang/entities/node.py
bigbang/entities/relationship.py
bigbang/repositories/__init__.py
bigbang/repositories/csv_2_node.py
bigbang/repositories/csv_2_pandas.py
bigbang/repositories/csv_2_relationship.py
bigbang/repositories/neo4j_driver.py
bigbang/repositories/node.py
bigbang/repositories/relationship.py
bigbang/usecases/__init__.py
bigbang/usecases/import_nodes.py
bigbang/usecases/import_relationships.py
neo4j_bigbang-0.0.25.dist-info/LICENSE
neo4j_bigbang-0.0.25.dist-info/METADATA
neo4j_bigbang-0.0.25.dist-info/WHEEL
neo4j_bigbang-0.0.25.dist-info/entry_points.txt
neo4j_bigbang-0.0.25.dist-info/top_level.txt
neo4j_bigbang-0.0.25.dist-info/RECORD
