Metadata-Version: 2.1
Name: neo4j-bigbang
Version: 0.0.25
Summary: This is a library allows you to import csv data into neo4j database
Home-page: https://github.com/euonymus/neo4j-bigbang
Author: euonymus
Author-email: euonymus0220@gmail.com
License: UNKNOWN
Platform: UNKNOWN
Classifier: Programming Language :: Python :: 3
Classifier: License :: OSI Approved :: MIT License
Classifier: Operating System :: OS Independent
Requires-Python: >=3.6
Requires-Dist: neo4j (>=4.1.1)
Requires-Dist: pandas (>=1.1.2)
Requires-Dist: python-dotenv (>=0.14.0)
Requires-Dist: pytest (>=6.0.2)
Requires-Dist: pytest-mock (>=3.3.1)
